OneBot12Adapter/Core.py
OneBot12Adapter/__init__.py
erispulse_onebot12adapter-1.0.2.dist-info/licenses/LICENSE
erispulse_onebot12adapter-1.0.2.dist-info/METADATA
erispulse_onebot12adapter-1.0.2.dist-info/WHEEL
erispulse_onebot12adapter-1.0.2.dist-info/entry_points.txt
erispulse_onebot12adapter-1.0.2.dist-info/top_level.txt
erispulse_onebot12adapter-1.0.2.dist-info/RECORD
