Metadata-Version: 2.4
Name: ErisPulse-OneBot12Adapter
Version: 1.0.2
Summary: ErisPulse的OneBotV12协议适配模块，基线协议适配器
Author-email: wsu2059q <wsu2059@qq.com>
License: MIT License
Project-URL: homepage, https://github.com/ErisPulse/ErisPulse-OneBot12Adapter
Keywords: erispulse,erispulse-adapter
Requires-Python: >=3.10
License-File: LICENSE
Dynamic: license-file
